<mods xmlns="http://www.loc.gov/mods/v3" xmlns:xsi="http://www.w3.org/2001/XMLSchema-instance" ID="Bodhi2000" xsi:schemaLocation="http://www.loc.gov/mods/v3 http://data.stonesutras.org:8080/exist/servlet/db/schema/mods-3-0.xsd">
    <titleInfo lang="en">
        <title>The Connected Discourses of the Buddha: A New Translation of the Saṃyutta Nikāya</title>
    </titleInfo>
    <titleInfo type="reference">
        <title>Bodhi 2000</title>
    </titleInfo>
    <name xmlns:oXygen2="http://www.w3.org/1999/xlink" oXygen2:href="#bodhi" type="personal">
        <namePart lang="fr" type="family">Bodhi</namePart>
        <namePart lang="fr" type="given">Bhikku</namePart>
        <role>
            <roleTerm>translator</roleTerm>
        </role>
    </name>
    <physicalDescription>
        <form>print</form>
        <extent>
            <detail type="volume">2</detail>
        </extent>
    </physicalDescription>
    <originInfo>
        <dateIssued>2000</dateIssued>
        <place>
            <placeTerm>Boston</placeTerm>
        </place>
        <publisher>
            <name type="corporate">
                <namePart lang="en">Wisdom Publications</namePart>
            </name>
        </publisher>
        <issuance>monographic</issuance>
    </originInfo>
    <relatedItem xmlns:ns2="http://www.w3.org/1999/xlink" ns2:href="" type="series">
        <titleInfo lang="en">
            <title>The Teachings of the Buddha</title>
        </titleInfo>
    </relatedItem>
</mods>