<?xml version="1.0" encoding="UTF-8"?>
<mods xmlns="http://www.loc.gov/mods/v3" xmlns:xsi="http://www.w3.org/2001/XMLSchema-instance" ID="Brown1998a" xsi:schemaLocation="http://www.loc.gov/mods/v3     http://data.stonesutras.org:8080/exist/servlet/db/schema/mods-3-0.xsd"><titleInfo lang="en"><title>Expected Miracles: The Unsurprisingly Miraculous Nature of Buddhist Images and Relics.</title></titleInfo><titleInfo type="reference"><title>Brown1998a</title></titleInfo><name xmlns:ns2="http://www.w3.org/1999/xlink" ns2:href="#brown" type="personal"><namePart lang="en" type="family">Brown</namePart><namePart lang="en" type="given">Robert L</namePart><role><roleTerm>author</roleTerm></role></name><typeOfResource>text</typeOfResource><relatedItem xmlns:ns2="http://www.w3.org/1999/xlink" ns2:href="#Davis1998" type="host"><titleInfo><title>Images, Miracles, and Authority in Asian Religious Traditions.</title></titleInfo><originInfo><issuance>monographic</issuance></originInfo><part><extent unit="page"><start>23</start><end>35</end></extent></part></relatedItem></mods>