<mods xmlns="http://www.loc.gov/mods/v3" xmlns:xsi="http://www.w3.org/2001/XMLSchema-instance" ID="xuzhoutiba" xsi:schemaLocation="http://www.loc.gov/mods/v3     http://data.stonesutras.org:8080/exist/servlet/db/schema/mods-3-0.xsd">
    <titleInfo lang="zh">
        <title>虚舟題跋</title>
    </titleInfo>
    <titleInfo transliteration="pinyin">
        <title>Xuzhou tiba</title>
    </titleInfo>
    <titleInfo lang="en" type="translated">
        <title>Colophones by Xuzhou</title>
    </titleInfo>
    <titleInfo type="reference" displayLabel="Jinshi wenzi bianyi">
        <title>Xuzhou tiba</title>
    </titleInfo>
    <name xmlns:oXygen2="http://www.w3.org/1999/xlink" oXygen2:href="#wangshu" type="personal">
        <namePart lang="zh" type="family">王
        </namePart>
        <namePart lang="zh" type="given">澍</namePart>
        <namePart type="date"/>
        <role>
            <roleTerm>author</roleTerm>
        </role>
    </name>
    <name xmlns:oXygen2="http://www.w3.org/1999/xlink" oXygen2:href="#songzeyuan" type="personal">
        <namePart lang="zh" type="family">宋</namePart>
        <namePart lang="zh" type="given">澤元</namePart>
        <namePart type="date"/>
        <role>
            <roleTerm>editor</roleTerm>
        </role>
    </name>
    <extension>10 <hi rend="italic">juan </hi>
        <foreign lang="zh">卷</foreign>
    </extension>
    <!--<physicalDescription>
        <extent>
            <detail type="fascicle">10</detail>
        </extent>
    </physicalDescription>-->
    <originInfo>
        <issuance>monographic</issuance>
    </originInfo>
    <relatedItem xmlns:oXygen2="http://www.w3.org/1999/xlink" oXygen2:href="SKSLXB" type="host">
        <titleInfo transliteration="pinyin">
            <title>Shike shiliao xinbian</title>
        </titleInfo>
        <titleInfo lang="zh">
            <title>石刻史料新編</title>
        </titleInfo>
        <extension>12 <hi rend="italic">juan </hi>
            <foreign lang="zh">卷</foreign>
        </extension>
        <!--<physicalDescription>
            <extent type="fascicle">12</extent>
        </physicalDescription>-->
        <typeOfResource collection="yes"/>
        <part>
            <detail level="1" type="series">
                <number>4</number>
            </detail>
            <detail level="2" type="volume">
                <number>6</number>
            </detail>
            <extent unit="page">
                <start>661</start>
                <end>762</end>
            </extent>
        </part>
    </relatedItem>
</mods>