<mods xmlns="http://www.loc.gov/mods/v3" xmlns:xsi="http://www.w3.org/2001/XMLSchema-instance" ID="Gregory1986" xsi:schemaLocation="http://www.loc.gov/mods/v3     http://data.stonesutras.org:8080/exist/servlet/db/schema/mods-3-0.xsd">
    <titleInfo lang="en">
        <title>Traditions of Meditation in Chinese Buddhism</title>
    </titleInfo>
    <titleInfo type="reference">
        <title>Gregory 1986</title>
    </titleInfo>
    <name xmlns:oXygen2="http://www.w3.org/1999/xlink" oXygen2:href="#gregory" type="personal">
        <namePart lang="en" type="family">Gregory</namePart>
        <namePart lang="en" type="given">Peter N.</namePart>
        <role>
            <roleTerm>editor</roleTerm>
        </role>
    </name>
    <originInfo>
        <dateIssued>1986</dateIssued>
        <place>
            <placeTerm>Honolulu</placeTerm>
        </place>
        <publisher>
            <name type="corporate">
                <namePart lang="en">University of Hawaii Press</namePart>
            </name>
        </publisher>
        <issuance>monographic</issuance>
    </originInfo>
    <relatedItem xmlns:oXygen2="http://www.w3.org/1999/xlink" oXygen2:href="#StudiesInEastAsianBuddhism" type="series">
        <titleInfo lang="en">
            <title><!--Kuroda Institute -->Studies in East Asian Buddhism</title>
        </titleInfo>
        <part>
            <detail type="volume">
                <number>4</number>
            </detail>
        </part>
    </relatedItem>
</mods>