<?xml version="1.0" encoding="UTF-8"?>
<mods xmlns="http://www.loc.gov/mods/v3" xmlns:xsi="http://www.w3.org/2001/XMLSchema-instance" xsi:schemaLocation="http://www.loc.gov/mods/v3 http://claudia:claudia@www.stonesutras.org:8080/exist/webdav/db/schema/mods-3-0.xsd" ID="CBC@">
    <titleInfo lang="en" rend="italic">
        <title>CBC@: Chinese Buddhist Canonical Attributions Database</title>
    </titleInfo>
    <titleInfo type="reference">
        <title>CBC@</title>
    </titleInfo>
    <name xmlns:ns2="http://www.w3.org/1999/xlink" ns2:href="#radich" type="personal">
        <namePart type="family">Radich</namePart>
        <namePart type="given">Michael</namePart>
        <role>
            <roleTerm>editor</roleTerm>
        </role>
    </name>
    <name xmlns:ns2="http://www.w3.org/1999/xlink" ns2:href="#norrish" type="personal">
        <namePart type="family">Norrish</namePart>
        <namePart type="given">Jamie</namePart>
        <role>
            <roleTerm>editor</roleTerm>
        </role>
    </name>
    <location>
        <url>https://dazangthings.nz/cbc/</url>
    </location>
</mods>