<mods xmlns="http://www.loc.gov/mods/v3" xmlns:xsi="http://www.w3.org/2001/XMLSchema-instance" ID="Changanzhi1784" xsi:schemaLocation="http://www.loc.gov/mods/v3     http://data.stonesutras.org:8080/exist/servlet/db/schema/mods-3-0.xsd">
    <titleInfo transliteration="pinyin">
        <title>Chang’an zhi</title>
    </titleInfo>
    <titleInfo lang="zh">
        <title>長安志</title>
    </titleInfo>
    <titleInfo type="translated" lang="en">
        <title>Chronicles of Chang’an</title>
    </titleInfo>
    <titleInfo type="reference" displayLabel="Chang'an zhi">
        <title>Chang’an zhi 1784</title>
    </titleInfo>
    <name xmlns:ns2="http://www.w3.org/1999/xlink" ns2:href="#zhaoyanruo" type="personal">
        <namePart lang="zh" type="family">趙</namePart>
        <namePart lang="zh" type="given">彥若</namePart>
        <role>
            <roleTerm>editor</roleTerm>
        </role>
    </name>
    <originInfo>
        <dateIssued>1784</dateIssued>
        <place>
            <placeTerm/>
        </place>
        <publisher/>
        <issuance>monographic</issuance>
    </originInfo>
</mods>