<?xml version="1.0" encoding="UTF-8"?>
<mods xmlns="http://www.loc.gov/mods/v3" xmlns:xsi="http://www.w3.org/2001/XMLSchema-instance" ID="ChouBrown1991" xsi:schemaLocation="http://www.loc.gov/mods/v3     http://data.stonesutras.org:8080/exist/servlet/db/schema/mods-3-0.xsd"><titleInfo lang="en"><title>Chinese Painting under the Qianlong Emperor: The Symposium Papers in Two Volumes</title></titleInfo><titleInfo type="reference"><title>Chou and Brown 1991</title></titleInfo><name xmlns:ns2="http://www.w3.org/1999/xlink" ns2:href="#chou" type="personal"><namePart lang="en" type="family">Chou</namePart><namePart lang="en" type="given">Ju-hsi</namePart><role><roleTerm>editor</roleTerm></role></name><name xmlns:oXygen2="http://www.w3.org/1999/xlink" oXygen2:href="#brown_c" type="personal"><namePart lang="en" type="family">Brown</namePart><namePart lang="en" type="given">Claudia</namePart><role><roleTerm>editor</roleTerm></role></name><relatedItem xmlns:oXygen2="http://www.w3.org/1999/xlink" oXygen2:href="#IndoIranianJournal" type="host"><titleInfo lang="en"><title>Phøebus, A Journal of Art History</title></titleInfo><originInfo><issuance>continuing</issuance></originInfo><part><detail type="volume">6</detail><detail type="no">2</detail><extent unit="page"><start>199</start><end>418</end></extent><date>1991</date></part></relatedItem></mods>