<mods xmlns="http://www.loc.gov/mods/v3" xmlns:xsi="http://www.w3.org/2001/XMLSchema-instance" ID="LDDWTSSK2006" xsi:schemaLocation="http://www.loc.gov/mods/v3 http://claudia:claudia@data.stonesutras.org:8080/exist/webdav/db/schema/mods-3-0.xsd">
    <titleInfo lang="zh">
        <title>歷代帝王泰山刻石</title>
    </titleInfo>
    <titleInfo transliteration="pinyin">
        <title>Lidai diwang taishan keshi</title>
    </titleInfo>
    <titleInfo type="translated" lang="en">
        <title>Historical Inscriptions of Emperors and Kings on Mount Tai</title>
    </titleInfo>
    <titleInfo type="reference">
        <title>Lidai diwang taishan keshi 2006</title>
    </titleInfo>
    <name xmlns:ns2="http://www.w3.org/1999/xlink" ns2:href="#ts_whys_jlzx" type="corporate">
        <namePart lang="zh">泰山文化藝術交流中心</namePart>
        <namePart transliteration="pinyin">Taishan wenhua yishu jiaoliu zhongxin</namePart>
        <role>
            <roleTerm>editor</roleTerm>
        </role>
    </name>
    <originInfo>
        <dateIssued>2006</dateIssued>
        <place>
            <placeTerm transliteration="pinyin">Beijing</placeTerm>
            <placeTerm lang="zh">北京</placeTerm>
        </place>
        <publisher>
            <name type="corporate">
                <namePart transliteration="pinyin">Zhongguo dang’an chubanshe</namePart>
                <namePart lang="zh">中國檔案出版社</namePart>
            </name>
        </publisher>
    </originInfo>
    <physicalDescription>
        <form>print</form>
        <extent>4 fascicles</extent>
    </physicalDescription>
</mods>