<?xml version="1.0" encoding="UTF-8"?>
<mods xmlns="http://www.loc.gov/mods/v3" xmlns:xsi="http://www.w3.org/2001/XMLSchema-instance" ID="Shangwu_xin_cidian" xsi:schemaLocation="http://www.loc.gov/mods/v3     http://data.stonesutras.org:8080/exist/servlet/db/schema/mods-3-0.xsd"><titleInfo transliteration="pinyin"><title>Shangwu xin cidian</title></titleInfo><titleInfo lang="zh"><title>商務新詞典</title></titleInfo><name xmlns:oXygen2="http://www.w3.org/1999/xlink" oXygen2:href="#huanggangsheng" type="personal"><namePart transliteration="pinyin" type="family">Huang</namePart><namePart transliteration="pinyin" type="given">Gangsheng</namePart><namePart lang="zh" type="family">黃</namePart><namePart lang="zh" type="given">港生</namePart><role><roleTerm>editor</roleTerm></role></name><originInfo><dateIssued>1990</dateIssued><place><placeTerm>Xianggang</placeTerm><placeTerm>香港</placeTerm></place><publisher><name type="corporate"><namePart lang="zh">商務印書館</namePart><namePart transliteration="pinyin">Shangwu yinshiguan</namePart></name></publisher></originInfo></mods>