<mods xmlns="http://www.loc.gov/mods/v3" xmlns:xsi="http://www.w3.org/2001/XMLSchema-instance" ID="Swanson2018" xsi:schemaLocation="http://www.loc.gov/mods/v3     http://data.stonesutras.org:8080/exist/servlet/db/schema/mods-3-0.xsd">
    <titleInfo lang="en">
        <title>Great Serenity, Quiet Insight: T’ian-T’ai Chih-i’s <hi rend="normal">Mo-ho
                Chih-kuan</hi>
        </title>
    </titleInfo>
    <titleInfo type="reference">
        <title>Swanson 2018</title>
    </titleInfo>
    <name xmlns:oXygen2="http://www.w3.org/1999/xlink" oXygen2:href="#swanson" type="personal">
        <namePart lang="en" type="family">Swanson</namePart>
        <namePart lang="en" type="given">Paul L.</namePart>
        <role>
            <roleTerm>translator</roleTerm>
        </role>
    </name>
    <originInfo>
        <place>
            <placeTerm lang="en">Honolulu</placeTerm>
        </place>
        <publisher>
            <name type="corporate">
                <namePart lang="en">University of Hawaiʻi Press</namePart>
            </name>
        </publisher>
        <dateIssued>2018</dateIssued>
        <issuance>monographic</issuance>
    </originInfo>
    <relatedItem xmlns:oXygen2="http://www.w3.org/1999/xlink" oXygen2:href="#NanzanLibrary" type="series">
        <titleInfo lang="en">
            <title>Nanzan Library of Asian Religion and Culture</title>
        </titleInfo>
    </relatedItem>
    <language>
        <languageTerm>english</languageTerm>
    </language>
    <extension>3 vols</extension>
</mods>