<?xml version="1.0" encoding="UTF-8"?>
<mods xmlns="http://www.loc.gov/mods/v3" xmlns:xsi="http://www.w3.org/2001/XMLSchema-instance" ID="Zacchetti2005" xsi:schemaLocation="http://www.loc.gov/mods/v3 http://sueyling:sueyling@data.stonesutras.org:8080/exist/webdav/db/schema/mods-3-0.xsd">
    
<titleInfo lang="en"><title>In Praise of the Light: A Critical Synoptic Edition with an Annotated Translation of Chapters 1–3 of <foreign lang="sa">Dharmarakṣa’s</foreign> Guang zan jing <foreign lang="zh">光讚經</foreign>, Being the Earliest Chinese Translation of the Larger <foreign lang="sa">Prajñāpāramitā</foreign></title></titleInfo>
    
    <titleInfo type="reference">
        <title>Zacchetti 2005</title>
    </titleInfo>
    <name xmlns:ns2="http://www.w3.org/1999/xlink" lang="en" ns2:href="#zacchetti" type="personal">
        <namePart lang="en" type="family">Zacchetti</namePart>
        <namePart lang="en" type="given">Stefano</namePart>
        <role>
            <roleTerm>author</roleTerm>
        </role>
    </name>
    <originInfo>
        <place>
            <placeTerm transliteration="romaji">Tōkyō</placeTerm>
        </place>
        <publisher>
            <name type="corporate">
                <namePart lang="en">The International Research Institute for Advanced Buddhology, Soka University</namePart>
            </name>
        </publisher>
        <issuance>monographic</issuance>
        <dateIssued>2005</dateIssued>
    </originInfo>
    <relatedItem type="series">
        <titleInfo lang="en">
            <title>Bibliotheca Philologica et Philosophica Buddhica 8</title>
        </titleInfo>
    </relatedItem>
</mods>